moxa_contr/__init__.py
moxa_contr/main.py
qodex_moxa_il1214-0.0.34.dist-info/METADATA
qodex_moxa_il1214-0.0.34.dist-info/WHEEL
qodex_moxa_il1214-0.0.34.dist-info/top_level.txt
qodex_moxa_il1214-0.0.34.dist-info/RECORD
