Metadata-Version: 2.1
Name: qodex-moxa-il1214
Version: 0.0.34
Author: PunchyArchy
Requires-Dist: requests
